odoo9_addon_mgmtsystem_info_security_manual-9.0.1.0.0-py2.7-nspkg.pth
odoo_addons/mgmtsystem_info_security_manual/__openerp__.py
odoo_addons/mgmtsystem_info_security_manual/__init__.py
odoo_addons/mgmtsystem_info_security_manual/README.rst
odoo_addons/mgmtsystem_info_security_manual/data/information_security_manual.xml
odoo_addons/mgmtsystem_info_security_manual/static/description/icon.png
odoo9_addon_mgmtsystem_info_security_manual-9.0.1.0.0.dist-info/top_level.txt
odoo9_addon_mgmtsystem_info_security_manual-9.0.1.0.0.dist-info/WHEEL
odoo9_addon_mgmtsystem_info_security_manual-9.0.1.0.0.dist-info/RECORD
odoo9_addon_mgmtsystem_info_security_manual-9.0.1.0.0.dist-info/metadata.json
odoo9_addon_mgmtsystem_info_security_manual-9.0.1.0.0.dist-info/DESCRIPTION.rst
odoo9_addon_mgmtsystem_info_security_manual-9.0.1.0.0.dist-info/METADATA
odoo9_addon_mgmtsystem_info_security_manual-9.0.1.0.0.dist-info/namespace_packages.txt
